computer/__init__.py
computer/computer.py
computer/diorama_computer.py
computer/helpers.py
computer/interface/__init__.py
computer/interface/android.py
computer/interface/base.py
computer/interface/factory.py
computer/interface/generic.py
computer/interface/linux.py
computer/interface/macos.py
computer/interface/models.py
computer/interface/windows.py
computer/logger.py
computer/models.py
computer/otel_wrapper.py
computer/providers/__init__.py
computer/providers/base.py
computer/providers/cloud/__init__.py
computer/providers/cloud/provider.py
computer/providers/docker/__init__.py
computer/providers/docker/provider.py
computer/providers/factory.py
computer/providers/lume/__init__.py
computer/providers/lume/provider.py
computer/providers/lume_api.py
computer/providers/lumier/__init__.py
computer/providers/lumier/provider.py
computer/providers/types.py
computer/providers/winsandbox/__init__.py
computer/providers/winsandbox/provider.py
computer/providers/winsandbox/setup_script.ps1
computer/tracing.py
computer/tracing_wrapper.py
computer/ui/__init__.py
computer/ui/__main__.py
computer/ui/gradio/__init__.py
computer/ui/gradio/app.py
computer/utils.py
cua_computer-0.5.12.dist-info/METADATA
cua_computer-0.5.12.dist-info/WHEEL
cua_computer-0.5.12.dist-info/entry_points.txt
cua_computer-0.5.12.dist-info/RECORD
