Metadata-Version: 2.1
Name: cua-computer
Version: 0.5.12
Summary: Computer-Use Interface (CUI) framework powering Cua
Author-Email: TryCua <gh@trycua.com>
Requires-Python: <3.14,>=3.12
Requires-Dist: pillow>=10.0.0
Requires-Dist: websocket-client>=1.8.0
Requires-Dist: websockets>=12.0
Requires-Dist: aiohttp>=3.9.0
Requires-Dist: cua-core<0.2.0,>=0.1.0
Requires-Dist: pydantic>=2.11.1
Requires-Dist: mslex>=1.3.0
Provides-Extra: lume
Provides-Extra: lumier
Provides-Extra: ui
Requires-Dist: gradio>=5.23.3; extra == "ui"
Requires-Dist: python-dotenv>=1.0.1; extra == "ui"
Requires-Dist: datasets>=3.6.0; extra == "ui"
Provides-Extra: all
Requires-Dist: gradio>=5.23.3; extra == "all"
Requires-Dist: python-dotenv>=1.0.1; extra == "all"
Requires-Dist: datasets>=3.6.0; extra == "all"
